src/__init__.py
src/gcproc/__init__.py
src/gcproc/gcproc.py
src/gcproc/experimential/__init__.py
src/gcproc/experimential/gcproc_catboost.py
src/gcproc/experimential/transfer.py
src/gcproc/test/__init__.py
src/gcproc/test/test_gcproc.py
src/gcproc/utils/__init__.py
src/gcproc/utils/derviation.py
src/gcproc/utils/missing_initializer.py
src/gcproc/utils/parameter_intialization.py
src/gcproc/utils/reader.py
GCProc-0.1.0.dist-info/LICENSE
GCProc-0.1.0.dist-info/METADATA
GCProc-0.1.0.dist-info/WHEEL
GCProc-0.1.0.dist-info/top_level.txt
GCProc-0.1.0.dist-info/RECORD
