Metadata-Version: 2.1
Name: GCProc
Version: 0.1.0
Summary: Python Implementation of the R-based GCProc
Home-page: https://github.com/thisismygitrepo/gcprocpy
Author: ['Alex Al-Saffar', 'David Banh']
Author-email: programmer@usa.com
License: MIT
Platform: UNKNOWN
Requires-Python: >=3.6
License-File: LICENSE
